onepm-24.3.dist-info/METADATA
onepm-24.3.dist-info/WHEEL
onepm-24.3.dist-info/entry_points.txt
onepm-24.3.dist-info/licenses/LICENSE
onepm/__init__.py
onepm/cli.py
onepm/core.py
onepm/pm/__init__.py
onepm/pm/base.py
onepm/pm/pdm.py
onepm/pm/pip.py
onepm/pm/pipenv.py
onepm/pm/poetry.py
onepm/pm/uv.py
onepm/py.typed
onepm-24.3.dist-info/RECORD
