Metadata-Version: 2.1
Name: onepm
Version: 24.3
Summary: Picks the right package manager for you
Author-Email: Frost Ming <mianghong@gmail.com>
License: MIT
Classifier: Topic :: Software Development :: Build Tools
Classifier: Programming Language :: Python :: 3
Classifier: Programming Language :: Python :: 3 :: Only
Classifier: Programming Language :: Python :: 3.10
Classifier: Programming Language :: Python :: 3.11
Classifier: Programming Language :: Python :: 3.12
Project-URL: Homepage, https://github.com/frostming/onepm
Project-URL: Repository, https://github.com/frostming/onepm
Project-URL: Changelog, https://github.com/frostming/onepm/releases
Requires-Python: >=3.10
Requires-Dist: packaging>=22.1
Requires-Dist: tomlkit>=0.12.3
Provides-Extra: shims
Requires-Dist: onepm-shims; extra == "shims"
